safecache.py
safecachedecorator-0.1.dist-info/METADATA
safecachedecorator-0.1.dist-info/WHEEL
safecachedecorator-0.1.dist-info/top_level.txt
safecachedecorator-0.1.dist-info/RECORD
