Metadata-Version: 2.1
Name: safecachedecorator
Version: 0.1
Summary: Thread-safe Python caching decorator with TTL
Home-page: https://github.com/Pappa1945-tech/SafeCacheDecorator
Author: Pappa1945-tech
Author-email: your_email@example.com
Classifier: Programming Language :: Python :: 3
Classifier: License :: OSI Approved :: MIT License
Requires-Python: >=3.6
